simpleparallelize/__init__.py
simpleparallelize/simple.py
simpleparallelize-0.1.4.dist-info/WHEEL
simpleparallelize-0.1.4.dist-info/METADATA
simpleparallelize-0.1.4.dist-info/RECORD
